fastapi_users_db_sqlmodel/__init__.py
fastapi_users_db_sqlmodel/access_token.py
fastapi_users_db_sqlmodel/generics.py
fastapi_users_db_sqlmodel/py.typed
fastapi_users_db_sqlmodel-0.2.0.dist-info/LICENSE
fastapi_users_db_sqlmodel-0.2.0.dist-info/WHEEL
fastapi_users_db_sqlmodel-0.2.0.dist-info/METADATA
fastapi_users_db_sqlmodel-0.2.0.dist-info/RECORD
