Metadata-Version: 2.1
Name: fastapi-users-db-sqlmodel
Version: 0.2.0
Summary: FastAPI Users database adapter for SQLModel.
Home-page: https://github.com/fastapi-users/fastapi-users-db-sqlmodel
Author: François Voron
Author-email: fvoron@gmail.com
Requires-Python: >=3.7
Classifier: License :: OSI Approved :: MIT License
Classifier: Development Status :: 5 - Production/Stable
Classifier: Framework :: AsyncIO
Classifier: Intended Audience :: Developers
Classifier: Programming Language :: Python :: 3.7
Classifier: Programming Language :: Python :: 3.8
Classifier: Programming Language :: Python :: 3.9
Classifier: Programming Language :: Python :: 3 :: Only
Classifier: Topic :: Internet :: WWW/HTTP :: Session
Requires-Dist: fastapi-users >= 10.0.2
Requires-Dist: sqlmodel
Requires-Dist: sqlalchemy[asyncio] >=1.4,<1.4.36
Project-URL: Documentation, https://fastapi-users.github.io/fastapi-users
